curvenote_template/DefBuilder.py
curvenote_template/DocModel.py
curvenote_template/LatexBuilder.py
curvenote_template/PublicTemplateLoader.py
curvenote_template/TemplateLoader.py
curvenote_template/TemplateOptions.py
curvenote_template/TemplateRenderer.py
curvenote_template/TexFormat.py
curvenote_template/__init__.py
curvenote_template/__main__.py
curvenote_template/utils.py
curvenote_template/version.py
curvenote_template/builtin_template/curvenote.png
curvenote_template/builtin_template/template.tex
curvenote_template/builtin_template/template.yml
curvenote_template/cli/__init__.py
curvenote_template/cli/app.py
curvenote_template/cli/build.py
curvenote_template/cli/build_lite.py
curvenote_template/cli/deprecated.py
curvenote_template/cli/validate.py
curvenote_template/defs/cmd-bibstyle-abbrvnat.def
curvenote_template/defs/cmd-citestyle-authoryear-rounded.def
curvenote_template/defs/cmd-raggedbottom.def
curvenote_template/defs/cmd-shortdate.def
curvenote_template/defs/cmd-sloppy.def
curvenote_template/defs/package-base.def
curvenote_template/defs/package-fancyvrb.def
curvenote_template/defs/package-mdframed.def
curvenote_template/defs/package-minted.def
curvenote_template/defs/package-natbib.def
curvenote_template/defs/package-xcolor.def
curvenote_template/defs/passopts-base.def
curvenote_template/defs/passopts-code-xcolor.def
curvenote_template/defs/passopts-mdframed.def
curvenote_template/defs/setup-aside-callout.def
curvenote_template/defs/setup-aside-framed.def
curvenote_template/defs/setup-aside-marginpar.def
curvenote_template/defs/setup-aside-mdframed.def
curvenote_template/defs/setup-base.def
curvenote_template/defs/setup-bib-style.def
curvenote_template/defs/setup-callout-framed.def
curvenote_template/defs/setup-callout-mdframed.def
curvenote_template/defs/setup-callout.def
curvenote_template/defs/setup-cite-style.def
curvenote_template/defs/setup-code-framed.def
curvenote_template/defs/setup-code-minted.def
curvenote_template/defs/setup-code-verbatim.def
curvenote_template-0.2.7.dist-info/LICENSE
curvenote_template-0.2.7.dist-info/METADATA
curvenote_template-0.2.7.dist-info/WHEEL
curvenote_template-0.2.7.dist-info/entry_points.txt
curvenote_template-0.2.7.dist-info/top_level.txt
curvenote_template-0.2.7.dist-info/RECORD
